{
  "dependencies": {
    "mssql1": {
      "secretStore": "AzureAppSettings",
      "resourceId": "/subscriptions/[parameters('subscriptionId')]/resourceGroups/[parameters('resourceGroupName')]/providers/Microsoft.Sql/servers/comp1640-db/databases/comp1640-db",
      "type": "mssql.azure",
      "connectionId": "ConnectionStrings:DefaultConnection"
    },
    "signalr1": {
      "secretStore": "AzureAppSettings",
      "resourceId": "/subscriptions/[parameters('subscriptionId')]/resourceGroups/[parameters('resourceGroupName')]/providers/Microsoft.SignalRService/SignalR/comp1640hub",
      "type": "signalr.azure",
      "connectionId": "Azure:SignalR:ConnectionString"
    }
  }
}